__init__.py
geocode.py
setup.py
geocode.egg-info/PKG-INFO
geocode.egg-info/SOURCES.txt
geocode.egg-info/dependency_links.txt
geocode.egg-info/top_level.txt