Metadata-Version: 1.0
Name: geocode
Version: 0.1.0
Summary: simple Python geocoding module using the Google Maps API
Home-page: https://github.com/bendmorris/python-geocode
Author: Ben Morris
Author-email: ben@bendmorris.com
License: UNKNOWN
Platform: UNKNOWN
